zkml/__init__.py
zkml/_computation_base.py
zkml/_helper.py
zkml/_input_generator.py
zkml/_leo_helper.py
zkml/_model_transpiler.py
zkml/leo_transpiler.py
zkml-0.0.2b2.dist-info/LICENSE.md
zkml-0.0.2b2.dist-info/METADATA
zkml-0.0.2b2.dist-info/WHEEL
zkml-0.0.2b2.dist-info/RECORD
