Metadata-Version: 2.3
Name: zkml
Version: 0.0.2b2
Summary: A transpiler for Python machine learning models to Leo for zero-knowledge inference
License: GPL-3.0
Author: Konstantin Pandl
Author-email: konstantin@aleo.org
Requires-Python: >=3.9,<4.0
Classifier: License :: OSI Approved :: GNU General Public License v3 (GPLv3)
Classifier: Programming Language :: Python :: 3
Classifier: Programming Language :: Python :: 3.9
Classifier: Programming Language :: Python :: 3.10
Classifier: Programming Language :: Python :: 3.11
Classifier: Programming Language :: Python :: 3.12
Classifier: Programming Language :: Python :: 3.13
Requires-Dist: numpy (>=1.24.3,<2.0.0)
Requires-Dist: pandas (>=2.1.0,<3.0.0)
Requires-Dist: psutil (>=5.8.0,<6.0.0)
Requires-Dist: scikit-learn (>=1.3.0,<2.0.0)
Project-URL: Repository, https://github.com/AleoHQ/python-sdk/tree/master/zkml
